[ {
  "Store Name" : "Greenpark",
  "Service Name" : "Dry Cleaning",
  "Service Type" : "Primary Service",
  "Amount without Tax & Discount" : "144339",
  "Quantity" : "617",
  "Pcs" : "626"
}, {
  "Store Name" : "Greenpark",
  "Service Name" : "Hanger",
  "Service Type" : "Top Up/Extra Service",
  "Amount without Tax & Discount" : "810",
  "Quantity" : "79",
  "Pcs" : "79"
}, {
  "Store Name" : "Greenpark",
  "Service Name" : "Premium Laundry",
  "Service Type" : "Primary Service",
  "Amount without Tax & Discount" : "14720",
  "Quantity" : "18",
  "Pcs" : "18"
}, {
  "Store Name" : "Greenpark",
  "Service Name" : "Leather Care",
  "Service Type" : "Primary Service",
  "Amount without Tax & Discount" : "55563",
  "Quantity" : "62",
  "Pcs" : "91"
}, {
  "Store Name" : "Greenpark",
  "Service Name" : "Steam Iron",
  "Service Type" : "Primary Service",
  "Amount without Tax & Discount" : "10295",
  "Quantity" : "77",
  "Pcs" : "90"
}, {
  "Store Name" : "Greenpark",
  "Service Name" : "Wash and Fold",
  "Service Type" : "Primary Service",
  "Amount without Tax & Discount" : "8037",
  "Quantity" : "14",
  "Pcs" : "14"
}, {
  "Store Name" : "Greenpark",
  "Service Name" : "Wash and Iron",
  "Service Type" : "Primary Service",
  "Amount without Tax & Discount" : "8640",
  "Quantity" : "13",
  "Pcs" : "13"
} ]