[ {
  "Store Name" : "Greenpark",
  "Service Name" : "Dry Cleaning",
  "Service Type" : "Primary Service",
  "Amount without Tax & Discount" : "84755",
  "Quantity" : "358",
  "Pcs" : "367"
}, {
  "Store Name" : "Greenpark",
  "Service Name" : "Hanger",
  "Service Type" : "Top Up/Extra Service",
  "Amount without Tax & Discount" : "480",
  "Quantity" : "46",
  "Pcs" : "46"
}, {
  "Store Name" : "Greenpark",
  "Service Name" : "Premium Laundry",
  "Service Type" : "Primary Service",
  "Amount without Tax & Discount" : "4960",
  "Quantity" : "7",
  "Pcs" : "7"
}, {
  "Store Name" : "Greenpark",
  "Service Name" : "Leather Care",
  "Service Type" : "Primary Service",
  "Amount without Tax & Discount" : "14962",
  "Quantity" : "18",
  "Pcs" : "26"
}, {
  "Store Name" : "Greenpark",
  "Service Name" : "Steam Iron",
  "Service Type" : "Primary Service",
  "Amount without Tax & Discount" : "6185",
  "Quantity" : "44",
  "Pcs" : "57"
}, {
  "Store Name" : "Greenpark",
  "Service Name" : "Wash and Fold",
  "Service Type" : "Primary Service",
  "Amount without Tax & Discount" : "6687",
  "Quantity" : "11",
  "Pcs" : "11"
}, {
  "Store Name" : "Greenpark",
  "Service Name" : "Wash and Iron",
  "Service Type" : "Primary Service",
  "Amount without Tax & Discount" : "2508",
  "Quantity" : "5",
  "Pcs" : "5"
} ]